sphinxcontrib/datatemplates/__init__.py
sphinxcontrib/datatemplates/cli.py
sphinxcontrib/datatemplates/directive.py
sphinxcontrib/datatemplates/domain.py
sphinxcontrib/datatemplates/helpers.py
sphinxcontrib/datatemplates/loaders.py
sphinxcontrib/datatemplates/version.py
sphinxcontrib.datatemplates-0.11.0.dist-info/LICENSE
sphinxcontrib.datatemplates-0.11.0.dist-info/METADATA
sphinxcontrib.datatemplates-0.11.0.dist-info/WHEEL
sphinxcontrib.datatemplates-0.11.0.dist-info/entry_points.txt
sphinxcontrib.datatemplates-0.11.0.dist-info/top_level.txt
sphinxcontrib.datatemplates-0.11.0.dist-info/RECORD
