Metadata-Version: 2.1
Name: sphinxcontrib.datatemplates
Version: 0.11.0
Summary: Sphinx extension for rendering data files as nice HTML
Author-email: Doug Hellmann <doug@doughellmann.com>
Project-URL: homepage, https://sphinxcontribdatatemplates.readthedocs.io/en/latest/
Project-URL: repository, http://github.com/sphinx-contrib/datatemplates
Classifier: Development Status :: 4 - Beta
Classifier: Environment :: Console
Classifier: Environment :: Web Environment
Classifier: Framework :: Sphinx :: Extension
Classifier: Intended Audience :: Developers
Classifier: License :: OSI Approved :: BSD License
Classifier: Operating System :: OS Independent
Classifier: Programming Language :: Python
Classifier: Programming Language :: Python :: 3.8
Classifier: Programming Language :: Python :: 3.9
Classifier: Programming Language :: Python :: 3.10
Classifier: Programming Language :: Python :: 3.11
Classifier: Programming Language :: Python :: 3.12
Classifier: Topic :: Documentation
Classifier: Topic :: Utilities
Requires-Python: >=3.8
License-File: LICENSE
Requires-Dist: Sphinx
Requires-Dist: PyYAML
Requires-Dist: defusedxml
Requires-Dist: sphinxcontrib-runcmd
Provides-Extra: build
Requires-Dist: build ; extra == 'build'
Requires-Dist: twine ; extra == 'build'
Provides-Extra: linter
Requires-Dist: flake8 ; extra == 'linter'
Provides-Extra: test
Requires-Dist: pytest ; extra == 'test'
Requires-Dist: beautifulsoup4 ; extra == 'test'
